{
  "name": "@nlux/nlbridge-react",
  "version": "{versions.nlux}",
  "license": "MPL-2.0",
  "description": "The nlbridge adapters for nlux React, the React JS library for building conversational AI interfaces.",
  "repository": {
    "directory": "packages/react/nlbridge"
  },
  "dependencies": {
    "@nlux/nlbridge": "^{versions.nlux}"
  },
  "peerDependencies": {
    "@nlux/react": "{versions.nlux}",
    "react": "^{versions.peerDependencies.react}"
  },
  "main": "index.js",
  "types": "nlbridge-react.d.ts",
  "module": "esm/nlbridge-react.js",
  "browser": "umd/nlbridge-react.js"
}
